mcp_mysql_ops/__init__.py
mcp_mysql_ops/__main__.py
mcp_mysql_ops/functions.py
mcp_mysql_ops/mcp_main.py
mcp_mysql_ops/version_compat.py
mcp_mysql_ops-1.3.2.dist-info/licenses/LICENSE
mcp_mysql_ops-1.3.2.dist-info/METADATA
mcp_mysql_ops-1.3.2.dist-info/WHEEL
mcp_mysql_ops-1.3.2.dist-info/entry_points.txt
mcp_mysql_ops-1.3.2.dist-info/top_level.txt
mcp_mysql_ops-1.3.2.dist-info/RECORD
