Metadata-Version: 2.4
Name: mcp-mysql-ops
Version: 1.3.2
Summary: MCP server for MySQL database operations and monitoring
Author-email: JungJungIn <call518@gmail.com>
Requires-Python: >=3.12
License-File: LICENSE
Requires-Dist: fastmcp>=2.12.3
Requires-Dist: aiomysql>=0.2.0
Requires-Dist: PyMySQL>=1.1.0
Requires-Dist: mcp>=1.13.0
Provides-Extra: dev
Requires-Dist: pytest>=7.0.0; extra == "dev"
Requires-Dist: pytest-asyncio>=0.21.0; extra == "dev"
Dynamic: license-file
